clias/__init__.py
clias/__main__.py
clias/cli.py
clias/run.py
clias-0.1.0a1.dist-info/LICENSE
clias-0.1.0a1.dist-info/METADATA
clias-0.1.0a1.dist-info/WHEEL
clias-0.1.0a1.dist-info/entry_points.txt
clias-0.1.0a1.dist-info/top_level.txt
clias-0.1.0a1.dist-info/RECORD
