Metadata-Version: 2.1
Name: clias
Version: 0.1.0a1
Summary: Turn shell script into cli command
Author: kj-9
License: Apache-2.0
Project-URL: Homepage, https://github.com/kj-9/clias
Project-URL: Changelog, https://github.com/kj-9/clias/releases
Project-URL: Issues, https://github.com/kj-9/clias/issues
Project-URL: CI, https://github.com/kj-9/clias/actions
Classifier: License :: OSI Approved :: Apache Software License
Requires-Python: >=3.9
License-File: LICENSE
Requires-Dist: click
Requires-Dist: jinja2 >=3.1.4
Requires-Dist: pyyaml >=6.0.2
Provides-Extra: test
Requires-Dist: pytest ; extra == 'test'
Requires-Dist: pre-commit ; extra == 'test'
Requires-Dist: cogapp ; extra == 'test'
